<?xml version="1.0" encoding="utf-8"?>
<!DOCTYPE hibernate-mapping PUBLIC
        "-//Hibernate/Hibernate Mapping DTD 3.0//EN"
        "http://hibernate.sourceforge.net/hibernate-mapping-3.0.dtd">
<!-- 
    Mapping file autogenerated by MyEclipse Persistence Tools
-->
<hibernate-mapping>
    <class name="com.sinojava.entity.StudentClassRecord" table="t_student_class_record" catalog="sinojavasys">
        <id name="rid" type="integer">
            <column name="rid" />
            <generator class="identity" />
        </id>
        <many-to-one name="stu" class="com.sinojava.entity.Student" fetch="join">
            <column name="sid">
                <comment>学生ID</comment>
            </column>
        </many-to-one>
        <many-to-one name="sc" class="com.sinojava.entity.Stuclass" fetch="join">
            <column name="cid">
                <comment>班级ID</comment>
            </column>
        </many-to-one>
        <property name="date" type="date">
            <column name="date" length="0">
                <comment>升班日期</comment>
            </column>
        </property>
    </class>
</hibernate-mapping>
